LICENSE
wire/__init__.py
wire/app.py
wire/enums.py
wire/groups/__init__.py
wire/groups/group.py
wire/listener.py
wire/plugs/__init__.py
wire/plugs/alternator.py
wire/plugs/eventable.py
wire/plugs/routable.py
wire/plugs/static.py
wire/request.py
wire/response.py
wire/router.py
wire/static.py
wire/templating.py
wire/typings.py
wire_web-0.3.2.dist-info/entry_points.txt
wire_web-0.3.2.dist-info/LICENSE
wire_web-0.3.2.dist-info/WHEEL
wire_web-0.3.2.dist-info/METADATA
wire_web-0.3.2.dist-info/RECORD
