Metadata-Version: 2.1
Name: wire-web
Version: 0.3.2
Summary: Wire the web
Home-page: https://wire.bernerdev.de/
License: MIT
Keywords: asgi,python,web,webdevelopment
Author: Leo B.
Author-email: bernerdoodle@outlook.de
Requires-Python: >=3.9,<4.0
Classifier: License :: OSI Approved :: MIT License
Classifier: Programming Language :: Python :: 3
Classifier: Programming Language :: Python :: 3.10
Classifier: Programming Language :: Python :: 3.9
Requires-Dist: multidict (>=5.1.0,<6.0.0)
Requires-Dist: pydantic (>=1.9.0,<2.0.0)
Requires-Dist: wire-fuchs (>=0.1.0,<0.2.0)
Requires-Dist: wire-rxtr (>=0.2,<0.3)
Project-URL: Chat, https://discord.gg/EtqGfBVuZS
Project-URL: Changes, https://wire.bernerdev.de/changelog
Project-URL: Repository, https://github.com/cheetahbyte/wire
